s3ctl/__init__.py
s3ctl/cli.py
s3ctl/count.py
s3ctl/date.py
s3ctl/main.py
s3ctl/name.py
s3ctl/size.py
s3ctl-0.1.12.dist-info/DESCRIPTION.rst
s3ctl-0.1.12.dist-info/METADATA
s3ctl-0.1.12.dist-info/RECORD
s3ctl-0.1.12.dist-info/WHEEL
s3ctl-0.1.12.dist-info/metadata.json
s3ctl-0.1.12.dist-info/top_level.txt
